brainfuck/__init__.py
brainfuck/brainfuck.py
brainfuck/test/__init__.py
brainfuck/test/main.py
brainfrick_language-0.1.dist-info/METADATA
brainfrick_language-0.1.dist-info/WHEEL
brainfrick_language-0.1.dist-info/entry_points.txt
brainfrick_language-0.1.dist-info/top_level.txt
brainfrick_language-0.1.dist-info/RECORD
